pynvidia/__init__.py
pynvidia/memory.py
pynvidia-0.1.0.dist-info/DESCRIPTION.rst
pynvidia-0.1.0.dist-info/METADATA
pynvidia-0.1.0.dist-info/RECORD
pynvidia-0.1.0.dist-info/WHEEL
pynvidia-0.1.0.dist-info/metadata.json
pynvidia-0.1.0.dist-info/top_level.txt
