Metadata-Version: 2.0
Name: pynvidia
Version: 0.1.0
Summary: NVIDIA GPU utilities for Python
Home-page: https://github.com/jaxony/pynvidia
Author: Jackson Huang
Author-email: jackson_huang@live.com
License: MIT
Keywords: Utilities,Deep Learning,NVIDIA,GPU
Platform: UNKNOWN
